jwtauthenticator/__init__.py
jwtauthenticator/jwtauthenticator.py
jupyterhub_jwtauthenticator_v2-2.0.3.dist-info/LICENSE
jupyterhub_jwtauthenticator_v2-2.0.3.dist-info/METADATA
jupyterhub_jwtauthenticator_v2-2.0.3.dist-info/WHEEL
jupyterhub_jwtauthenticator_v2-2.0.3.dist-info/top_level.txt
jupyterhub_jwtauthenticator_v2-2.0.3.dist-info/RECORD
