Metadata-Version: 2.1
Name: jupyterhub-jwtauthenticator-v2
Version: 2.0.3
Summary: JSONWebToken Authenticator for JupyterHub
Home-page: https://github.com/izihawa/jwtauthenticator_v2
Author: ppodolsky
Author-email: ppodolsky@me.com
License: Apache 2.0
Platform: UNKNOWN
Requires-Dist: jupyterhub
Requires-Dist: pyjwt
